pyhelpers_daevski/__init__.py
pyhelpers_daevski/QuickCommand.py
pyhelpers_daevski/security.py
pyhelpers_daevski-0.3.2.dist-info/METADATA
pyhelpers_daevski-0.3.2.dist-info/WHEEL
pyhelpers_daevski-0.3.2.dist-info/RECORD
